OddEvenSP/OddEvenSP.py
OddEvenSP/__init__.py
oddeven_sp-3.0.1.dist-info/METADATA
oddeven_sp-3.0.1.dist-info/WHEEL
oddeven_sp-3.0.1.dist-info/top_level.txt
oddeven_sp-3.0.1.dist-info/RECORD
