Metadata-Version: 2.4
Name: OddEven-SP
Version: 3.0.1
Summary: So, welcome to my first ever Python Project! That is a game based on Odd Even, but with a twist of Cricket!
Author-email: Aarav Gupta <tribejustice35@gmail.com>
License: Apache Software License
Project-URL: Homepage, https://github.com/Aarav2709/OddEven-SP
Keywords: OddEven,SinglePlayer,Game,Cricket,Python
Classifier: Development Status :: 5 - Production/Stable
Classifier: License :: OSI Approved :: Apache Software License
Classifier: Programming Language :: Python :: 3.13
Classifier: Intended Audience :: Education
Classifier: Operating System :: OS Independent
Requires-Python: >=3.6
